[
  {
  "name": "ebs-volume-fault-tolerance",
  "description": "EBS volume does not have a snapshot within the last 7 days",
  "resource": "ebs"
  },
  {
    "recommendation": "",
    "key_fields": [
      {"Encrypted": "Encrypted"},
      {"Attached Instance": ""},
      {"Volume ID": "Attachments[VolumeID]"},
      {"Volume Availability Zone": "AvailabilityZone"},
      {"Availability Zone": "AvailabilityZone"}
    ],
    "categories": [
      "backup-dr",
      ""
    ],
    "priority": [
      {"Default": "High"},
      {"SOC 2": "High"},
      {"HIPAA": "Medium"},
      {"ISO 27001": "Medium"},
      {"GDPR": "Medium"}
    ],
    "compliance_mappings": [
      {"SOC 2": [ "CC6.1", "CC6.2" ]},
      {"HIPAA": [ "TECH-1", "TECH-2" ]},
      {"ISO 27001": [ "ISO-1", "ISO-2" ]},
      {"GDPR": [ "GDPR-1", "GDPR-2" ]}
    ]
  }
]
